cptv_rs_python_bindings/__init__.py
cptv_rs_python_bindings/cptv_rs_python_bindings.cpython-311-aarch64-linux-gnu.so
python_cptv-0.0.8.dist-info/METADATA
python_cptv-0.0.8.dist-info/WHEEL
python_cptv-0.0.8.dist-info/RECORD
