Metadata-Version: 2.4
Name: python-cptv
Version: 0.0.8
Classifier: Programming Language :: Python :: 3
Classifier: License :: OSI Approved :: MIT License
Classifier: Operating System :: OS Independent
Requires-Dist: numpy
Summary: This is Python package provides for quick parsing Cacophony Project Thermal Video (CPTV) files. 
Author-email: Jon Hardie <Jon@cacophony.org.nz>, Giampaolo Feraro <Giampaolo@Cacophony.org.nz>
Requires-Python: >=3.8
